nonebot_plugin_phlogo/__init__.py
nonebot_plugin_phlogo/logo.py
nonebot_plugin_phlogo/resource/font.ttf
nonebot_plugin_phlogo-0.0.3.dist-info/LICENSE
nonebot_plugin_phlogo-0.0.3.dist-info/WHEEL
nonebot_plugin_phlogo-0.0.3.dist-info/METADATA
nonebot_plugin_phlogo-0.0.3.dist-info/RECORD
