Metadata-Version: 2.1
Name: nonebot-plugin-phlogo
Version: 0.0.3
Summary: 生成ph风格logo
Home-page: https://github.com/kexue-z/nonebot-plugin-phlogo
License: MIT
Author: kexue
Author-email: x@kexue.io
Requires-Python: >=3.7.3
Classifier: License :: OSI Approved :: MIT License
Classifier: Programming Language :: Python :: 3
Classifier: Programming Language :: Python :: 3.8
Classifier: Programming Language :: Python :: 3.9
Classifier: Programming Language :: Python :: 3.10
Classifier: Programming Language :: Python :: 3.11
Requires-Dist: Pillow (>=8.3.1)
Requires-Dist: nonebot2 (>=2.0.0-beta.1)
